nhv/__init__.py
nhv/layer/__init__.py
nhv/layer/incremental.py
nhv/layer/layer.py
nhv/layer/model.py
nhv/layer/module.py
nhv/layer/preprocess.py
neural_homomorphic_vocoder-0.0.13.dist-info/LICENSE
neural_homomorphic_vocoder-0.0.13.dist-info/METADATA
neural_homomorphic_vocoder-0.0.13.dist-info/WHEEL
neural_homomorphic_vocoder-0.0.13.dist-info/top_level.txt
neural_homomorphic_vocoder-0.0.13.dist-info/RECORD
