Metadata-Version: 2.1
Name: neural-homomorphic-vocoder
Version: 0.0.13
Summary: Pytorch implementation of neural homomorphic vocoder
Home-page: https://github.com/k2kobayashi/neural-homomorphic-vocoder
Author: K. KOBAYASHI
License: MIT
Platform: UNKNOWN
Requires-Dist: numpy (>=1.20.3)
Requires-Dist: torch (>=1.8.0)
Requires-Dist: torchvision (>=0.9.0)
Requires-Dist: torchaudio (>=0.8.0)
Requires-Dist: librosa (==0.8.0)
Requires-Dist: onnxruntime
Requires-Dist: h5py
